getmac/__init__.py
getmac/__main__.py
getmac/getmac.py
getmac/shutilwhich.py
get_mac-0.9.1.dist-info/LICENSE
get_mac-0.9.1.dist-info/METADATA
get_mac-0.9.1.dist-info/WHEEL
get_mac-0.9.1.dist-info/entry_points.txt
get_mac-0.9.1.dist-info/top_level.txt
get_mac-0.9.1.dist-info/zip-safe
get_mac-0.9.1.dist-info/RECORD
