Metadata-Version: 2.1
Name: get-mac
Version: 0.9.1
Summary: Get MAC addresses of remote hosts and local interfaces
Home-page: https://github.com/GhostofGoes/getmac
Author: Christopher Goes
Author-email: ghostofgoes@gmail.com
License: MIT
Project-URL: Changelog, https://github.com/GhostofGoes/getmac/blob/main/CHANGELOG.md
Project-URL: Issue tracker, https://github.com/GhostofGoes/getmac/issues
Project-URL: Source, https://github.com/GhostofGoes/getmac
Project-URL: Discord server, https://discord.gg/python
Keywords: getmac,get-mac,macaddress,mac-address,mac,ethernet,mac-48,networking,network,networking,layer2,layer-2,802.3
Classifier: Development Status :: 4 - Beta
Classifier: Environment :: Console
Classifier: License :: OSI Approved :: MIT License
Classifier: Operating System :: OS Independent
Classifier: Operating System :: Microsoft :: Windows
Classifier: Operating System :: POSIX
Classifier: Operating System :: MacOS
Classifier: Programming Language :: Python
Classifier: Programming Language :: Python :: 3
Classifier: Programming Language :: Python :: 3.4
Classifier: Programming Language :: Python :: 3.5
Classifier: Programming Language :: Python :: 3.6
Classifier: Programming Language :: Python :: 3.7
Classifier: Programming Language :: Python :: 3.8
Classifier: Programming Language :: Python :: 3.9
Classifier: Programming Language :: Python :: 3.10
Classifier: Programming Language :: Python :: 3.11
Classifier: Programming Language :: Python :: 2
Classifier: Programming Language :: Python :: 2.7
Classifier: Programming Language :: Python :: Implementation :: CPython
Classifier: Programming Language :: Python :: Implementation :: PyPy
Classifier: Programming Language :: Python :: Implementation :: IronPython
Classifier: Programming Language :: Python :: Implementation :: Jython
Classifier: Intended Audience :: Developers
Classifier: Intended Audience :: System Administrators
Classifier: Intended Audience :: Information Technology
Classifier: Topic :: Software Development :: Libraries :: Python Modules
Classifier: Topic :: Software Development :: Libraries
Classifier: Topic :: System :: Systems Administration
Classifier: Topic :: System :: Networking
Classifier: Topic :: Utilities
Requires-Python: >=2.7, !=3.0.*, !=3.1.*, !=3.2.*, !=3.3.*
License-File: LICENSE
